deploywizard/__init__.py
deploywizard/cli.py
deploywizard/scaffolder/__init__.py
deploywizard/scaffolder/api_generator.py
deploywizard/scaffolder/docker_generator.py
deploywizard/scaffolder/model_loader.py
deploywizard/scaffolder/model_registry.py
deploywizard/scaffolder/scaffolder.py
deploywizard/scaffolder/template_utils.py
deploywizard/templates/Dockerfile.tpl
deploywizard/templates/__init__.py
deploywizard/templates/docker-compose.tpl
deploywizard/templates/fastapi_main.tpl
deploywizard-0.3.1.1.dist-info/licenses/LICENSE
deploywizard-0.3.1.1.dist-info/METADATA
deploywizard-0.3.1.1.dist-info/WHEEL
deploywizard-0.3.1.1.dist-info/entry_points.txt
deploywizard-0.3.1.1.dist-info/top_level.txt
deploywizard-0.3.1.1.dist-info/RECORD
