Metadata-Version: 2.4
Name: deploywizard
Version: 0.3.1.1
Summary: A CLI tool for deploying ML models as production-ready REST APIs
Author-email: Hemant Sirsat <hemantsirsat40@gmail.com>
License: MIT
Project-URL: Homepage, https://github.com/hemantsirsat/deploywizard
Project-URL: Bug Tracker, https://github.com/hemantsirsat/deploywizard/issues
Classifier: Development Status :: 3 - Alpha
Classifier: Intended Audience :: Developers
Classifier: Intended Audience :: Science/Research
Classifier: License :: OSI Approved :: MIT License
Classifier: Programming Language :: Python :: 3.9
Classifier: Programming Language :: Python :: 3.10
Classifier: Programming Language :: Python :: 3.11
Classifier: Topic :: Scientific/Engineering
Classifier: Topic :: Scientific/Engineering :: Artificial Intelligence
Classifier: Topic :: Software Development
Classifier: Topic :: Software Development :: Libraries :: Python Modules
Requires-Python: >=3.9
License-File: LICENSE
Requires-Dist: fastapi>=0.68.0
Requires-Dist: uvicorn>=0.15.0
Requires-Dist: pydantic<3.0.0,>=1.8.2
Requires-Dist: typer>=0.4.0
Requires-Dist: jinja2>=3.0.0
Requires-Dist: joblib>=1.0.0
Requires-Dist: numpy>=1.21.0
Requires-Dist: torch>=1.9.0
Requires-Dist: scikit-learn>=1.0.0
Requires-Dist: tensorflow>=2.6.0; platform_system != "Windows" or python_version < "3.11"
Provides-Extra: dev
Requires-Dist: pytest>=6.0; extra == "dev"
Requires-Dist: pytest-cov>=4.0.0; extra == "dev"
Requires-Dist: pytest-xdist>=3.0.0; extra == "dev"
Requires-Dist: black>=21.0; extra == "dev"
Requires-Dist: isort>=5.0; extra == "dev"
Requires-Dist: mypy>=0.910; extra == "dev"
Requires-Dist: flake8>=3.9.0; extra == "dev"
Requires-Dist: types-requests>=2.31.0; extra == "dev"
Requires-Dist: pytest-mock>=3.0.0; extra == "dev"
Provides-Extra: test
Requires-Dist: pytest>=6.0; extra == "test"
Requires-Dist: pytest-cov>=4.0.0; extra == "test"
Requires-Dist: pytest-xdist>=3.0.0; extra == "test"
Requires-Dist: pytest-mock>=3.0.0; extra == "test"
Provides-Extra: lint
Requires-Dist: black>=21.0; extra == "lint"
Requires-Dist: isort>=5.0; extra == "lint"
Requires-Dist: mypy>=0.910; extra == "lint"
Requires-Dist: flake8>=3.9.0; extra == "lint"
Dynamic: license-file
